adhands_api/adhands_api.py
adhands_api/__init__.py
adhands_api-0.1.1.dist-info/METADATA
adhands_api-0.1.1.dist-info/top_level.txt
adhands_api-0.1.1.dist-info/RECORD
adhands_api-0.1.1.dist-info/WHEEL
adhands_api-0.1.1.dist-info/DESCRIPTION.rst
adhands_api-0.1.1.dist-info/metadata.json
