Metadata-Version: 2.0
Name: adhands-api
Version: 0.1.1
Summary: Python 3 client library to use adhands api
Home-page: https://github.com/MrEhbr/adhands_api
Author: adhands_api
Author-email: mr.ehbr@gmail.com
License: ISCL
Keywords: adhands_api
Platform: UNKNOWN
Classifier: Development Status :: 2 - Pre-Alpha
Classifier: Intended Audience :: Developers
Classifier: License :: OSI Approved :: ISC License (ISCL)
Classifier: Natural Language :: English
Classifier: Programming Language :: Python :: 2
Classifier: Programming Language :: Python :: 2.6
Classifier: Programming Language :: Python :: 2.7
Classifier: Programming Language :: Python :: 3
Classifier: Programming Language :: Python :: 3.3
Classifier: Programming Language :: Python :: 3.4
Requires-Dist: requests
